{
  "_class": "shapePath",
  "booleanOperation": -1,
  "do_objectID": "D3626268-E3B8-4A05-9E34-938D69A290D6",
  "edited": true,
  "exportOptions": {
    "_class": "exportOptions",
    "exportFormats": [
    ],
    "includedLayerIds": [
    ],
    "layerOptions": 0,
    "shouldTrim": false
  },
  "frame": {
    "_class": "rect",
    "constrainProportions": false,
    "height": 7.969372607234932,
    "width": 7.969372607234927,
    "x": 0.937573247909992,
    "y": 0.9375732479099914
  },
  "isFlippedHorizontal": false,
  "isFlippedVertical": false,
  "isLocked": false,
  "isVisible": true,
  "layerListExpandedType": 0,
  "name": "48-path",
  "nameIsFixed": false,
  "path": {
    "_class": "path",
    "isClosed": true,
    "pointRadiusBehaviour": 0,
    "points": [
      {
        "_class": "curvePoint",
        "cornerRadius": 0,
        "curveFrom": "{0, 0.22429411764705812}",
        "curveMode": 4,
        "curveTo": "{0, 0.5}",
        "hasCurveFrom": true,
        "hasCurveTo": false,
        "point": "{0, 0.5}"
      },
      {
        "_class": "curvePoint",
        "cornerRadius": 0,
        "curveFrom": "{0.77558823529411447, 0}",
        "curveMode": 2,
        "curveTo": "{0.22411764705882031, 0}",
        "hasCurveFrom": true,
        "hasCurveTo": true,
        "point": "{0.5, 0}"
      },
      {
        "_class": "curvePoint",
        "cornerRadius": 0,
        "curveFrom": "{1, 0.77570588235294191}",
        "curveMode": 2,
        "curveTo": "{1, 0.22429411764705812}",
        "hasCurveFrom": true,
        "hasCurveTo": true,
        "point": "{1, 0.5}"
      },
      {
        "_class": "curvePoint",
        "cornerRadius": 0,
        "curveFrom": "{0.22411764705882031, 1}",
        "curveMode": 2,
        "curveTo": "{0.77558823529411447, 1}",
        "hasCurveFrom": true,
        "hasCurveTo": true,
        "point": "{0.5, 1}"
      },
      {
        "_class": "curvePoint",
        "cornerRadius": 0,
        "curveFrom": "{0, 0.5}",
        "curveMode": 4,
        "curveTo": "{0, 0.77570588235294191}",
        "hasCurveFrom": false,
        "hasCurveTo": true,
        "point": "{0, 0.5}"
      }
    ]
  },
  "resizingConstraint": 63,
  "resizingType": 0,
  "rotation": 0,
  "shouldBreakMaskChain": false
}