{
  "_class": "symbolMaster",
  "backgroundColor": {
    "_class": "color",
    "alpha": 1,
    "blue": 1,
    "green": 1,
    "red": 1
  },
  "changeIdentifier": 885,
  "do_objectID": "EB71E09E-DE34-4439-B03E-9E84AC770179",
  "exportOptions": {
    "_class": "exportOptions",
    "exportFormats": [
    ],
    "includedLayerIds": [
    ],
    "layerOptions": 0,
    "shouldTrim": false
  },
  "frame": {
    "_class": "rect",
    "constrainProportions": false,
    "height": 29,
    "width": 375,
    "x": 13663,
    "y": -11
  },
  "hasBackgroundColor": true,
  "hasClickThrough": true,
  "horizontalRulerData": {
    "_class": "rulerData",
    "base": 0,
    "guides": [
    ]
  },
  "includeBackgroundColorInExport": true,
  "includeBackgroundColorInInstance": false,
  "includeInCloudUpload": true,
  "isFlippedHorizontal": false,
  "isFlippedVertical": false,
  "isLocked": false,
  "isVisible": true,
  "layerListExpandedType": 2,
  "layers": [
    {
      "class": "shapeGroup",
      "id": "027ED236-2CC9-4AB3-943C-D5F6D02AF065"
    },
    {
      "class": "shapeGroup",
      "id": "4EA5B619-7155-43D1-85F0-5D757A4E9156"
    },
    {
      "class": "text",
      "id": "D257B14D-47B3-4B14-9221-F0EFEE2A856D"
    },
    {
      "class": "symbolInstance",
      "id": "113A8A07-9B28-4497-AED8-F44C08DE236A"
    }
  ],
  "name": "paradas-way",
  "nameIsFixed": true,
  "resizesContent": false,
  "resizingConstraint": 63,
  "resizingType": 0,
  "rotation": 0,
  "shouldBreakMaskChain": true,
  "style": {
    "_class": "style",
    "endDecorationType": 0,
    "miterLimit": 10,
    "startDecorationType": 0
  },
  "symbolID": "2DE643B6-8289-41A1-AE74-EAA6702BD991",
  "userInfo": {
    "com.sketchapp.slinky-plugin": {
      "hrefURL": ""
    }
  },
  "verticalRulerData": {
    "_class": "rulerData",
    "base": 0,
    "guides": [
      248
    ]
  }
}