{
  "_class": "shapePath",
  "booleanOperation": -1,
  "do_objectID": "54E95221-ED2C-40CB-9E9F-5BA3994F39C7",
  "edited": true,
  "exportOptions": {
    "_class": "exportOptions",
    "exportFormats": [
    ],
    "includedLayerIds": [
    ],
    "layerOptions": 0,
    "shouldTrim": false
  },
  "frame": {
    "_class": "rect",
    "constrainProportions": false,
    "height": 0.8127532467532507,
    "width": 0.8631848552338539,
    "x": 0,
    "y": 2.842170943040402e-14
  },
  "isFlippedHorizontal": false,
  "isFlippedVertical": false,
  "isLocked": false,
  "isVisible": true,
  "layerListExpandedType": 0,
  "name": "Path",
  "nameIsFixed": false,
  "path": {
    "_class": "path",
    "isClosed": true,
    "pointRadiusBehaviour": 0,
    "points": [
      {
        "_class": "curvePoint",
        "cornerRadius": 0,
        "curveFrom": "{1.0466754392754853, 0.65907769007062844}",
        "curveMode": 4,
        "curveTo": "{0.960832881801997, 0.70872455338595852}",
        "hasCurveFrom": true,
        "hasCurveTo": false,
        "point": "{0.960832881801997, 0.70872455338595852}"
      },
      {
        "_class": "curvePoint",
        "cornerRadius": 0,
        "curveFrom": "{1, 0.63240548400498675}",
        "curveMode": 4,
        "curveTo": "{0.90846814768944983, 0.66422933111757465}",
        "hasCurveFrom": false,
        "hasCurveTo": true,
        "point": "{1, 0.63240548400498675}"
      },
      {
        "_class": "curvePoint",
        "cornerRadius": 0,
        "curveFrom": "{0.68225094821580634, 0.044121312837557679}",
        "curveMode": 4,
        "curveTo": "{0.80927316355755097, 0}",
        "hasCurveFrom": true,
        "hasCurveTo": false,
        "point": "{0.80927316355755097, 0}"
      },
      {
        "_class": "curvePoint",
        "cornerRadius": 0,
        "curveFrom": "{0.29085068503754169, 0.25571250519318695}",
        "curveMode": 3,
        "curveTo": "{0.55762829940397884, 0.10132945575405054}",
        "hasCurveFrom": true,
        "hasCurveTo": true,
        "point": "{0.43884975617307848, 0.17004570004154529}"
      },
      {
        "_class": "curvePoint",
        "cornerRadius": 0,
        "curveFrom": "{0, 0.51292064810967986}",
        "curveMode": 4,
        "curveTo": "{0.13909745336326321, 0.37428334025758203}",
        "hasCurveFrom": false,
        "hasCurveTo": true,
        "point": "{0, 0.51292064810967986}"
      },
      {
        "_class": "curvePoint",
        "cornerRadius": 0,
        "curveFrom": "{0.52264107129034731, 0.89912754466140543}",
        "curveMode": 4,
        "curveTo": "{0.42139484480222955, 1}",
        "hasCurveFrom": true,
        "hasCurveTo": false,
        "point": "{0.42139484480222955, 1}"
      },
      {
        "_class": "curvePoint",
        "cornerRadius": 0,
        "curveFrom": "{0.960832881801997, 0.70872455338595852}",
        "curveMode": 4,
        "curveTo": "{0.85842557473488657, 0.76800997091815726}",
        "hasCurveFrom": false,
        "hasCurveTo": true,
        "point": "{0.960832881801997, 0.70872455338595852}"
      }
    ]
  },
  "resizingConstraint": 63,
  "resizingType": 0,
  "rotation": 0,
  "shouldBreakMaskChain": false
}